gunicorn_thrift/__init__.py
gunicorn_thrift/config.py
gunicorn_thrift/gevent_worker.py
gunicorn_thrift/six.py
gunicorn_thrift/sync_worker.py
gunicorn_thrift/thriftapp.py
gunicorn_thrift/thriftpy_gevent_worker.py
gunicorn_thrift/thriftpy_sync_worker.py
gunicorn_thrift/utils.py
gunicorn_thrift-0.2.25.dist-info/LICENSE
gunicorn_thrift-0.2.25.dist-info/METADATA
gunicorn_thrift-0.2.25.dist-info/WHEEL
gunicorn_thrift-0.2.25.dist-info/entry_points.txt
gunicorn_thrift-0.2.25.dist-info/top_level.txt
gunicorn_thrift-0.2.25.dist-info/RECORD
