Metadata-Version: 2.1
Name: gunicorn-thrift
Version: 0.2.25
Summary: Thrift server using gunicorn
Home-page: UNKNOWN
Author: Haochuan Guo
Author-email: guohaochuan@gmail.com
License: MIT
Platform: UNKNOWN
Classifier: Development Status :: 3 - Alpha
Classifier: Environment :: Other Environment
Classifier: Intended Audience :: Developers
Classifier: License :: OSI Approved :: MIT License
Classifier: Operating System :: MacOS :: MacOS X
Classifier: Operating System :: POSIX
Classifier: Programming Language :: Python
Classifier: Programming Language :: Python :: 2.7
Classifier: Programming Language :: Python :: 3.4
Classifier: Programming Language :: Python :: 3.5
Classifier: Programming Language :: Python :: 3.6
Classifier: Programming Language :: Python :: 3.7
Classifier: Topic :: Utilities
Classifier: Topic :: Software Development :: Libraries :: Python Modules
Requires-Dist: setproctitle (==1.1.10)
Requires-Dist: gevent (<1.5,>=1.4)
Requires-Dist: gunicorn (==19.9.0)
Requires-Dist: thriftpy2 (>=0.4.0)
